planai/__init__.py
planai/_version.py
planai/cached_task.py
planai/chat_task.py
planai/cli.py
planai/cli_cache.py
planai/cli_optimize_prompt.py
planai/cli_utils.py
planai/debugging/debug_helpers.py
planai/dispatcher.py
planai/graph.py
planai/graph_task.py
planai/integrations/__init__.py
planai/integrations/browse.py
planai/integrations/search.py
planai/joined_task.py
planai/llm_task.py
planai/media_task.py
planai/merged_task.py
planai/patterns/__init__.py
planai/patterns/planner.py
planai/patterns/search_fetch.py
planai/provenance.py
planai/pydantic_dict_wrapper.py
planai/static/js/core.js
planai/static/js/graphs.js
planai/static/js/index.js
planai/static/js/memory.js
planai/static/js/mermaid.js
planai/static/js/status.js
planai/static/js/tasks.js
planai/static/js/theme.js
planai/static/js/trace.js
planai/static/js/utils.js
planai/static/js/workers.js
planai/static/styles.css
planai/stats.py
planai/task.py
planai/templates/index.html
planai/testing/__init__.py
planai/testing/helpers.py
planai/user_input.py
planai/utils.py
planai/web_interface.py
planai-0.6.1.dist-info/METADATA
planai-0.6.1.dist-info/WHEEL
planai-0.6.1.dist-info/entry_points.txt
planai-0.6.1.dist-info/licenses/LICENSE
planai-0.6.1.dist-info/RECORD
