Metadata-Version: 2.4
Name: planai
Version: 0.6.1
Summary: A simple framework for coordinating classical compute and LLM-based tasks.
License: Apache-2.0
License-File: LICENSE
Keywords: ai,automation,workflow,llm
Author: Niels Provos
Author-email: planai@provos.org
Requires-Python: >=3.10,<4.0
Classifier: Intended Audience :: Developers
Classifier: License :: OSI Approved :: Apache Software License
Classifier: Operating System :: OS Independent
Classifier: Programming Language :: Python :: 3
Classifier: Programming Language :: Python :: 3.10
Classifier: Programming Language :: Python :: 3.11
Classifier: Programming Language :: Python :: 3.12
Classifier: Programming Language :: Python :: 3.13
Classifier: Programming Language :: Python :: 3.14
Classifier: Topic :: Software Development :: Libraries :: Python Modules
Provides-Extra: docs
Requires-Dist: beautifulsoup4 (>=4.12.3,<5.0.0)
Requires-Dist: colorama (>=0.4.6,<0.5.0)
Requires-Dist: dicttoxml (>=1.7.16,<2.0.0)
Requires-Dist: diskcache (>=5.6.3,<6.0.0)
Requires-Dist: flask (>=3.1.2,<4.0.0)
Requires-Dist: html2text (>=2024.2.26,<2025.0.0)
Requires-Dist: llm-interface (>=0.1.13,<0.2.0)
Requires-Dist: playwright (>=1.49.1,<2.0.0)
Requires-Dist: psutil (>=6.1.1,<7.0.0)
Requires-Dist: pydantic (>=2.8.2,<3.0.0)
Requires-Dist: python-dotenv (>=1.0.1,<2.0.0)
Requires-Dist: waitress (>=3.0.2,<4.0.0)
Project-URL: Documentation, https://planai.readthedocs.io
Project-URL: Repository, https://github.com/provos/planai
